setup.py
ostinato_light/__init__.py
ostinato_light/drone.py
ostinato_light/port_list.py
ostinato_light/stream.py
ostinato_light/stream_list.py
ostinato_light.egg-info/PKG-INFO
ostinato_light.egg-info/SOURCES.txt
ostinato_light.egg-info/dependency_links.txt
ostinato_light.egg-info/requires.txt
ostinato_light.egg-info/top_level.txt
ostinato_light/protocols/__init__.py
ostinato_light/protocols/arp.py
ostinato_light/protocols/dot2llc.py
ostinato_light/protocols/dot2snap.py
ostinato_light/protocols/dot3.py
ostinato_light/protocols/ethernet.py
ostinato_light/protocols/fileformat.py
ostinato_light/protocols/hexdump.py
ostinato_light/protocols/icmp.py
ostinato_light/protocols/igmp.py
ostinato_light/protocols/ip4.py
ostinato_light/protocols/ip4over4.py
ostinato_light/protocols/ip4over6.py
ostinato_light/protocols/ip6.py
ostinato_light/protocols/ip6over4.py
ostinato_light/protocols/ip6over6.py
ostinato_light/protocols/llc.py
ostinato_light/protocols/mac.py
ostinato_light/protocols/payload.py
ostinato_light/protocols/sample.py
ostinato_light/protocols/snap.py
ostinato_light/protocols/tcp.py
ostinato_light/protocols/text_protocol.py
ostinato_light/protocols/udp.py
ostinato_light/protocols/userscript.py
ostinato_light/protocols/vlan.py
ostinato_light/protocols/vlan_stack.py
ostinato_light/protocols/base/__init__.py
ostinato_light/protocols/base/consts.py
ostinato_light/protocols/base/nseted_field_base.py
ostinato_light/protocols/base/protocol_base.py
ostinato_light/protocols/base/utils.py