Metadata-Version: 1.0
Name: ostinato-light
Version: 0.1.6
Summary: use ostinato in a more elegant way, python3 is incompatible
Home-page: http://www.jxyowen.cn
Author: jxyowen
Author-email: 506092147@qq.com
License: MIT License
Keywords: wrapper,ostinato
Platform: any
